briefkasten/__init__.py
briefkasten/commands.py
briefkasten/dropbox.py
briefkasten/housekeeping.py
briefkasten/notifications.py
briefkasten/testing.py
briefkasten/views.py
briefkasten/locale/briefkasten.pot
briefkasten/locale/de/LC_MESSAGES/briefkasten.mo
briefkasten/locale/de/LC_MESSAGES/briefkasten.po
briefkasten/templates/dropbox_form.pt
briefkasten/templates/editor_email.j2
briefkasten/templates/editor_reply.pt
briefkasten/templates/feedback.pt
briefkasten/templates/master.pt
briefkasten/tests/attachment.png
briefkasten/tests/attachment.txt
briefkasten/tests/conftest.py
briefkasten/tests/test_dropbox.py
briefkasten/tests/test_dropbox_cleanup.py
briefkasten/tests/test_editor_access.py
briefkasten/tests/test_janitor.py
briefkasten/tests/test_replies.py
briefkasten/tests/test_settings.py
briefkasten/tests/test_submission.py
briefkasten/tests/test_watchdog.py
briefkasten/tests/unicode.txt
briefkasten/tests/bin/process-attachments.sh
briefkasten/tests/drop_root_template/settings.yaml
briefkasten/tests/gpghome/.gitignore
briefkasten/tests/gpghome/pubring.gpg
briefkasten/tests/gpghome/pubring.gpg~
briefkasten/tests/gpghome/secring.gpg
briefkasten/tests/gpghome/trustdb.gpg
briefkasten-0.4.0.dist-info/METADATA
briefkasten-0.4.0.dist-info/WHEEL
briefkasten-0.4.0.dist-info/entry_points.txt
briefkasten-0.4.0.dist-info/top_level.txt
briefkasten-0.4.0.dist-info/RECORD
