Metadata-Version: 2.4
Name: briefkasten
Version: 0.4.0
Summary: a reasonably secure web application for submitting content anonymously
Maintainer-email: Tom Lazar <tom@tomster.org>
Requires-Dist: Pyramid<2.1
Requires-Dist: pyramid_chameleon
Requires-Dist: click
Requires-Dist: colander
Requires-Dist: diazo
Requires-Dist: humanfriendly
Requires-Dist: itsdangerous
Requires-Dist: jinja2
Requires-Dist: python-gnupg
Requires-Dist: repoze.xmliter
Requires-Dist: Paste
Requires-Dist: watchdog
Requires-Dist: PyYAML
